lssr/__init__.py
lssr/__main__.py
lssr/cli.py
lssr/core.py
lssr/util.py
lssr-1.3.0.dist-info/LICENSE
lssr-1.3.0.dist-info/METADATA
lssr-1.3.0.dist-info/WHEEL
lssr-1.3.0.dist-info/entry_points.txt
lssr-1.3.0.dist-info/RECORD
