Metadata-Version: 2.3
Name: lssr
Version: 1.3.0
Summary: Alternative ls command.
License: MIT
Author: seijinrosen
Author-email: 86702775+seijinrosen@users.noreply.github.com
Requires-Python: >=3.9,<4.0
Classifier: License :: OSI Approved :: MIT License
Classifier: Programming Language :: Python :: 3
Classifier: Programming Language :: Python :: 3.9
Classifier: Programming Language :: Python :: 3.10
Classifier: Programming Language :: Python :: 3.11
Classifier: Programming Language :: Python :: 3.12
Classifier: Programming Language :: Python :: 3.13
Requires-Dist: rich (>=12.4.4,<14.0.0)
Project-URL: Documentation, https://github.com/seijinrosen/lssr
Project-URL: Homepage, https://github.com/seijinrosen
Project-URL: Repository, https://github.com/seijinrosen/lssr
